hex_toolkit/__init__.py
hex_toolkit/auth.py
hex_toolkit/cli.py
hex_toolkit/client.py
hex_toolkit/config.py
hex_toolkit/exceptions.py
hex_toolkit/py.typed
hex_toolkit/mcp/__init__.py
hex_toolkit/mcp/config.py
hex_toolkit/mcp/installer.py
hex_toolkit/mcp/server.py
hex_toolkit/models/__init__.py
hex_toolkit/models/base.py
hex_toolkit/models/embedding.py
hex_toolkit/models/projects.py
hex_toolkit/models/runs.py
hex_toolkit/models/semantic_models.py
hex_toolkit/resources/__init__.py
hex_toolkit/resources/base.py
hex_toolkit/resources/embedding.py
hex_toolkit/resources/projects.py
hex_toolkit/resources/runs.py
hex_toolkit/resources/semantic_models.py
hex_toolkit-0.6.0.dist-info/METADATA
hex_toolkit-0.6.0.dist-info/WHEEL
hex_toolkit-0.6.0.dist-info/entry_points.txt
hex_toolkit-0.6.0.dist-info/licenses/LICENSE
hex_toolkit-0.6.0.dist-info/RECORD
