Metadata-Version: 2.4
Name: hex-toolkit
Version: 0.6.0
Summary: A comprehensive toolkit for working with Hex: SDK, CLI, and MCP integration
Project-URL: Homepage, https://github.com/franccesco/hex-toolkit
Project-URL: Documentation, https://hex-toolkit.readthedocs.io
Project-URL: Repository, https://github.com/franccesco/hex-toolkit
Project-URL: Issues, https://github.com/franccesco/hex-toolkit/issues
Author-email: Franccesco Orozco <franccesco@codingdose.info>
License: MIT
License-File: LICENSE
Classifier: Development Status :: 3 - Alpha
Classifier: Intended Audience :: Developers
Classifier: License :: OSI Approved :: MIT License
Classifier: Programming Language :: Python :: 3
Classifier: Programming Language :: Python :: 3.10
Classifier: Programming Language :: Python :: 3.11
Classifier: Programming Language :: Python :: 3.12
Requires-Python: >=3.10
Requires-Dist: httpx>=0.25.0
Requires-Dist: pydantic>=2.0
Requires-Dist: python-dateutil>=2.8.2
Requires-Dist: typing-extensions>=4.8.0
Provides-Extra: all
Requires-Dist: fastmcp>=1.0.0; extra == 'all'
Requires-Dist: rich>=13.5.0; extra == 'all'
Requires-Dist: typer>=0.9.0; extra == 'all'
Provides-Extra: cli
Requires-Dist: rich>=13.5.0; extra == 'cli'
Requires-Dist: typer>=0.9.0; extra == 'cli'
Provides-Extra: dev
Requires-Dist: jsonschema>=4.0.0; extra == 'dev'
Requires-Dist: pre-commit>=3.3.0; extra == 'dev'
Requires-Dist: pytest-cov>=4.1.0; extra == 'dev'
Requires-Dist: pytest-mock>=3.11.0; extra == 'dev'
Requires-Dist: pytest>=7.4.0; extra == 'dev'
Requires-Dist: ruff>=0.1.0; extra == 'dev'
Provides-Extra: mcp
Requires-Dist: fastmcp>=1.0.0; extra == 'mcp'
